auto_garch/__init__.py
auto_garch/auto_garch.py
auto_garch-0.1.0a0.dist-info/licenses/LICENSE
auto_garch-0.1.0a0.dist-info/METADATA
auto_garch-0.1.0a0.dist-info/WHEEL
auto_garch-0.1.0a0.dist-info/top_level.txt
auto_garch-0.1.0a0.dist-info/RECORD
