Metadata-Version: 2.4
Name: auto-garch
Version: 0.1.0a0
Summary: Regime-aware volatility modeling with automatic GARCH fitting
Author: Noah Woltman
License: MIT
Project-URL: Homepage, https://github.com/GuardsGuards/auto-garch
Requires-Python: >=3.9
License-File: LICENSE
Requires-Dist: numpy
Requires-Dist: pandas
Requires-Dist: matplotlib
Requires-Dist: scikit-learn
Requires-Dist: arch
Dynamic: license-file
